{
    "308": {
        "고제규": "76097",
        "김다은": "76098",
        "김동인": "76141",
        "김세욱": "80622",
        "김연희": "76099",
        "김영화": "76100",
        "김은지": "76101",
        "나경희": "76103",
        "문상현": "76105",
        "박미소": "79400",
        "변진경": "76106",
        "신선영": "76107",
        "이명익": "76108",
        "이상원": "76109",
        "이오성": "76110",
        "이은기": "76493",
        "이종태": "76111",
        "이한울": "80621",
        "임지영": "76112",
        "장일호": "76113",
        "전혜원": "76114",
        "정희상": "76115",
        "조남진": "76167",
        "주하은": "76494",
        "차형석": "76116",
        "최한솔": "76096"
    }
}