{
    "655": {
        "구준회": "77054",
        "김근혁": "79205",
        "김성은": "79526",
        "김세희": "76982",
        "김유찬": "78027",
        "김종기": "77090",
        "김준수": "79224",
        "박수범": "81063",
        "박언": "77089",
        "박희성": "76980",
        "송신의": "79209",
        "신현종": "77067",
        "안정은": "77061",
        "이민아": "76978",
        "이윤영": "77082",
        "이천기": "79204",
        "이태현": "76977",
        "장원석": "77057",
        "조상우": "77056",
        "조용광": "77080",
        "조용은": "80826",
        "주홍정": "79223",
        "채현석": "80850",
        "최병천": "77078",
        "홍우표": "77093"
    }
}